batchedffmpeg/__init__.py
batchedffmpeg/batchedffmpeg.py
batchedffmpeg-0.0.0.5.dist-info/LICENSE
batchedffmpeg-0.0.0.5.dist-info/METADATA
batchedffmpeg-0.0.0.5.dist-info/WHEEL
batchedffmpeg-0.0.0.5.dist-info/entry_points.txt
batchedffmpeg-0.0.0.5.dist-info/top_level.txt
batchedffmpeg-0.0.0.5.dist-info/RECORD
