Metadata-Version: 2.1
Name: batchedffmpeg
Version: 0.0.0.5
Summary: Process multiple videos with one line of ffmpeg command.
Home-page: https://github.com/developer0hye/BatchedFFmpeg
Author: Yonghye Kwon
Author-email: developer.0hye@gmail.com
License: UNKNOWN
Keywords: image,img,video,ffmpeg,media
Platform: UNKNOWN
Classifier: Programming Language :: Python :: 3
Classifier: License :: OSI Approved :: MIT License
Classifier: Operating System :: OS Independent
Requires-Python: >=3.6
License-File: LICENSE
